{
	"version" : 6,
	"name" : "scene_sibnek",
	"spawn player" : false,
	"camera" : 
	{
		"type" : "debug",
		"near plane" : 0.500000,
		"far plane" : 10000.000000,
		"fov" : 0.785398,
		"aperture" : 1.000000,
		"shutter speed" : 0.125000,
		"light sensitivity" : 800.000000,
		"exposure" : 1.200000,
		"move speed" : 18.000000,
		"transform" : 
		{
			"position" : "-57.448, 3.466, 7.706",
			"pitch" : 0.169489,
			"yaw" : -0.028459
		}
	},
	"objects" : 
	[
		{
			"name" : "Skybox",
			"id" : "9E21BB97E67E608D4AD74FCC0530F8D3",
			"type" : "skybox",
			"casts shadow" : false,
			"materials" : 
			[
				"skybox 01"
			],
			"skybox info" : 
			{
			}
		},
		{
			"name" : "Reflection Probe 01",
			"id" : "45440631ED0751AE443997FF4A39A977",
			"type" : "reflection probe",
			"transform" : 
			{
				"pos" : "0.000, 8.000, 0.000"
			}
		},
		{
			"name" : "sibnek",
			"id" : "E7C75C7194CDF4B24C2DFCEF17A6C45A",
			"type" : "object",
			"transform" : 
			{
				"pos" : "0.000, 45.000, 0.000",
				"scale" : "3.000, 3.000, 3.000"
			},
			"mesh" : "sibnek.glb",
			"materials" : 
			[
				"grid",
				"grid",
				"grid",
				"grid",
				"grid",
				"grid",
				"grid",
				"grid",
				"grid",
				"grid",
				"grid",
				"grid",
				"grid",
				"grid",
				"grid",
				"grid",
				"grid",
				"grid",
				"grid"
			]
		},
		{
			"name" : "PointLight_00",
			"id" : "EA160EA47EA0A5BC40042E4E323A40D4",
			"type" : "point light",
			"transform" : 
			{
				"pos" : "31.500, 18.434, 0.000",
				"rot" : "0.000, 0.065, 0.000"
			},
			"point light info" : 
			{
				"pos" : "31.500,18.434,0.000",
				"colour" : "1.00,1.00,1.00",
				"enabled" : true,
				"brightness" : 885.416992
			}
		},
		{
			"name" : "PointLight_01",
			"id" : "17F3514BFAAE13AE4539EDDE82D4C942",
			"type" : "point light",
			"transform" : 
			{
				"pos" : "-42.000, 15.400, 0.000"
			},
			"point light info" : 
			{
				"pos" : "-42.000,15.400,0.000",
				"colour" : "1.00,1.00,1.00",
				"enabled" : true,
				"brightness" : 640.625000
			}
		}
	]
}