{
	"version" : 1,
	"name" : "Scene Empty",
	"objects" : 
	[
		{
			"name" : "Cornell Box",
			"type" : "object",
			"visible" : true,
			"transform" : 
			{
				"pos" : "-28.690, 0.000, -0.001",
				"rot" : "1.570, 1.570, 3.141",
				"scale" : "19.999, 20.000, 19.999"
			},
			"mesh" : "cornell-box",
			"material" : "cornell"
		},
		{
			"name" : "Reflection Probe 01",
			"type" : "reflection probe",
			"visible" : false,
			"transform" : 
			{
				"pos" : "0.000, 18.600, 0.000"
			},
			"material" : "pbr chrome"
		},
		{
			"name" : "Skybox",
			"type" : "skybox",
			"visible" : true,
			"transform" : 
			{
			},
			"material" : "skybox 02",
			"skybox info" : 
			{
			}
		},
		{
			"name" : "Morph",
			"type" : "object",
			"visible" : true,
			"transform" : 
			{
				"pos" : "8.442, 2.794, 6.157",
				"scale" : "1.000, 5.360, 5.350"
			},
			"mesh" : "morph-tpose-01",
			"material" : "pbr white"
		}
		{
			"name" : "PointLight_01",
			"type" : "point light",
			"visible" : true,
			"transform" : 
			{
				"pos" : "2, 0, 0"
			},
			"point light info" : 
			{
				"pos" : "1, 0, 0",
				"color" : "0.49, 0.78, 0.91",
				"enabled" : true,
				"brightness" : 182.266006
			}
		},
		{
			"name" : "Directional Light",
			"type" : "directional light",
			"visible" : true,
			"transform" : 
			{
				"pos" : "0.000, 15.000, 0.000",
				"rot" : "1.195, -0.973, -2.522"
			},
			"directional light info" : 
			{
				"rotation" : "1.195, -0.973, -2.522",
				"pos" : "0.000, 15.000, 0.000",
				"color" : "1.00, 1.00, 1.00",
				"enabled" : true,
				"brightness" : 50.000000,
				"cast shadows" : true,
				"shadow darkness" : 0.000000,
				"shadow map near" : 0.000000,
				"shadow map far" : 100.000000,
				"shadow map zoom" : 1.000000
			}
		}
	]
}